asyncpg_trek/__init__.py
asyncpg_trek/_backend.py
asyncpg_trek/_collect.py
asyncpg_trek/_run.py
asyncpg_trek/_solver.py
asyncpg_trek/_types.py
asyncpg_trek/_typing.py
asyncpg_trek/aiosqlite.py
asyncpg_trek/asyncpg.py
asyncpg_trek-0.4.0.dist-info/LICENSE.txt
asyncpg_trek-0.4.0.dist-info/METADATA
asyncpg_trek-0.4.0.dist-info/WHEEL
asyncpg_trek-0.4.0.dist-info/RECORD
