Metadata-Version: 2.1
Name: asyncpg-trek
Version: 0.4.0
Summary: A simple migrations system for asyncpg
Home-page: https://github.com/adriangb/asyncpg-trek
License: MIT
Keywords: asyncpg,postgres,postgresql,migrations
Author: Adrian Garcia Badaracco
Author-email: adrian@adriangb.com
Requires-Python: >=3.8,<4
Classifier: Development Status :: 3 - Alpha
Classifier: Environment :: Web Environment
Classifier: Framework :: AsyncIO
Classifier: Intended Audience :: Developers
Classifier: Intended Audience :: Information Technology
Classifier: Intended Audience :: System Administrators
Classifier: License :: OSI Approved :: MIT License
Classifier: Operating System :: OS Independent
Classifier: Programming Language :: Python
Classifier: Programming Language :: Python :: 3
Classifier: Programming Language :: Python :: 3.8
Classifier: Programming Language :: Python :: 3.9
Classifier: Programming Language :: Python :: 3.10
Classifier: Programming Language :: Python :: 3.11
Classifier: Programming Language :: Python :: 3.12
Classifier: Programming Language :: Python :: 3 :: Only
Classifier: Programming Language :: Python :: 3.7
Classifier: Typing :: Typed
Provides-Extra: aiosqlite
Provides-Extra: asyncpg
Requires-Dist: aiosqlite (>=0.20.0) ; extra == "aiosqlite"
Requires-Dist: asyncpg (>=0.26.0) ; extra == "asyncpg"
Requires-Dist: typing_extensions (>=4) ; python_version < "3.8"
Project-URL: Documentation, https://github.com/adriangb/asyncpg-trek
Project-URL: Repository, https://github.com/adriangb/asyncpg-trek
